{
  "paging": {
    "page": 1,
    "count": 1,
    "maxPage": 1,
    "itemsTotal": 1
  },
  "packages": [
    {
      "id": "com.truonggia.stremioweb",
      "title": "Stremio Web",
      "iconUri": "https://raw.githubusercontent.com/TGiaDo/StremioWeb-Repository/main/assets/icon.png",
      "manifest": {
        "id": "com.truonggia.stremioweb",
        "version": "0.3.0",
        "type": "web",
        "title": "Stremio Web",
        "appDescription": "Stremio Web for LG webOS",
        "iconUri": "https://raw.githubusercontent.com/TGiaDo/StremioWeb-Repository/main/assets/icon.png",
        "sourceUrl": "https://github.com/TGiaDo/StremioWeb-v1",
        "rootRequired": true,
        "ipkUrl": "https://raw.githubusercontent.com/TGiaDo/StremioWeb-Repository/main/packages/com.truonggia.stremioweb_0.3.0_all.ipk",
        "ipkHash": {
          "sha256": "1504841ddd270bc460d1ebb5e0ad018bd8ca1ebb4fd53c9c9791109768ac1d8a"
        },
        "ipkSize": 3953970
      },
      "pool": "main",
      "shortDescription": "Stremio Web for LG webOS"
    }
  ]
}
